phiterm/__init__.py
phiterm/api/__init__.py
phiterm/api/client.py
phiterm/api/exceptions.py
phiterm/api/handler.py
phiterm/api/routes.py
phiterm/api/user.py
phiterm/api/workspace.py
phiterm/aws/__init__.py
phiterm/aws/aws_operator.py
phiterm/cli/__init__.py
phiterm/cli/cli_app.py
phiterm/cli/cli_operator.py
phiterm/cli/dx/__init__.py
phiterm/cli/dx/dx_app.py
phiterm/cli/gcp/__init__.py
phiterm/cli/gcp/gcp_app.py
phiterm/cli/gcp/gke/__init__.py
phiterm/cli/gcp/gke/gke_app.py
phiterm/cli/k8s/__init__.py
phiterm/cli/k8s/k8s_app.py
phiterm/cli/wf/__init__.py
phiterm/cli/wf/wf_app.py
phiterm/cli/ws/__init__.py
phiterm/cli/ws/ws_app.py
phiterm/conf/__init__.py
phiterm/conf/auth.py
phiterm/conf/constants.py
phiterm/conf/phi_conf.py
phiterm/databox/__init__.py
phiterm/databox/databox_operator.py
phiterm/docker/__init__.py
phiterm/docker/docker_operator.py
phiterm/enums/__init__.py
phiterm/enums/user.py
phiterm/k8s/__init__.py
phiterm/k8s/k8s_operator.py
phiterm/k8s/k8s_schemas.py
phiterm/k8s/tbd_k8s_operator.py
phiterm/k8s/tbd_k8s_ops.py
phiterm/k8s/tbd_k8s_utils.py
phiterm/k8s/tbd_phi_k8s_data.py
phiterm/local/__init__.py
phiterm/local/local_operator.py
phiterm/release/__init__.py
phiterm/release/release_enums.py
phiterm/release/release_schemas.py
phiterm/release/ws_releases.py
phiterm/schemas/__init__.py
phiterm/schemas/response.py
phiterm/schemas/user.py
phiterm/schemas/user_schemas.py
phiterm/schemas/workspace.py
phiterm/tbd/backend_api/__init__.py
phiterm/tbd/backend_api/api_client.py
phiterm/tbd/backend_api/api_exceptions.py
phiterm/tbd/backend_api/api_utils.py
phiterm/tbd/backend_api/auth_api.py
phiterm/tbd/backend_api/workspace_api.py
phiterm/tbd/tbd_gcp/__init__.py
phiterm/tbd/tbd_gcp/gcp_enums.py
phiterm/tbd/tbd_gcp/gcp_operator.py
phiterm/tbd/tbd_gcp/gcp_schemas.py
phiterm/tbd/tbd_gcp/gcp_utils.py
phiterm/tbd/tbd_gcp/gcp_zones.py
phiterm/tbd/tbd_gcp/phi_gcp_data.py
phiterm/tbd/tbd_gcp/tbd_gcp_ops.py
phiterm/tbd/tbd_gcp/gke/__init__.py
phiterm-1.7.9.dist-info/LICENSE.md
phiterm-1.7.9.dist-info/METADATA
phiterm-1.7.9.dist-info/WHEEL
phiterm-1.7.9.dist-info/entry_points.txt
phiterm-1.7.9.dist-info/top_level.txt
phiterm-1.7.9.dist-info/RECORD
